lerobot_lebai/__init__.py
lerobot_lebai/config_lebai.py
lerobot_lebai/lebai.py
lerobot_lebai-0.0.3.dist-info/licenses/LICENSE
lerobot_lebai-0.0.3.dist-info/METADATA
lerobot_lebai-0.0.3.dist-info/WHEEL
lerobot_lebai-0.0.3.dist-info/top_level.txt
lerobot_lebai-0.0.3.dist-info/RECORD
