Metadata-Version: 2.4
Name: lerobot_lebai
Version: 0.0.3
Summary: LeRobot Lebai integration
Author-email: Lebai Robotics <contact@lebai.ltd>
License:                                  Apache License
Classifier: Programming Language :: Python :: 3
Classifier: License :: OSI Approved :: Apache Software License
Classifier: Operating System :: OS Independent
Requires-Python: >=3.10
License-File: LICENSE
Requires-Dist: lebai-sdk
Requires-Dist: numpy
Requires-Dist: transforms3d
Requires-Dist: teleop
Requires-Dist: lerobot>=0.4
Dynamic: license-file
